teryt_tree/.gitignore
teryt_tree/__init__.py
teryt_tree/admin.py
teryt_tree/apps.py
teryt_tree/autocomplete_light_registry.py
teryt_tree/factories.py
teryt_tree/models.py
teryt_tree/dal_ext/__init__.py
teryt_tree/dal_ext/filters.py
teryt_tree/dal_ext/views.py
teryt_tree/filters_ext/__init__.py
teryt_tree/filters_ext/filters.py
teryt_tree/locale/pl/LC_MESSAGES/django.po
teryt_tree/management/__init__.py
teryt_tree/management/commands/__init__.py
teryt_tree/management/commands/load_simc.py
teryt_tree/management/commands/load_terc.py
teryt_tree/migrations/0001_initial.py
teryt_tree/migrations/0002_auto_20151216_0201.py
teryt_tree/migrations/0003_auto_20161210_1515.py
teryt_tree/migrations/0004_auto_20170712_2335.py
teryt_tree/migrations/0005_auto_20191020_1938.py
teryt_tree/migrations/0006_auto_20191020_1953.py
teryt_tree/migrations/0007_auto_20191020_2005.py
teryt_tree/migrations/__init__.py
teryt_tree/rest_framework_ext/__init__.py
teryt_tree/rest_framework_ext/serializers.py
teryt_tree/rest_framework_ext/viewsets.py
django_teryt_tree-0.18.4.dist-info/AUTHORS.rst
django_teryt_tree-0.18.4.dist-info/LICENSE
django_teryt_tree-0.18.4.dist-info/METADATA
django_teryt_tree-0.18.4.dist-info/WHEEL
django_teryt_tree-0.18.4.dist-info/top_level.txt
django_teryt_tree-0.18.4.dist-info/RECORD
