Metadata-Version: 2.1
Name: django-teryt-tree
Version: 0.18.4
Summary: Django-teryt-tree is a Django app that implements TERYT database as tree by django-mptt.
Home-page: https://github.com/ad-m/django-teryt-tree
Download-URL: https://github.com/ad-m/django-teryt-tree/
Author: Adam Dobrawy
Author-email: Adam Dobrawy <adam.dobrawy@siecobywatelska.pl>
License: BSD 3-Clause License
Keywords: django-teryt-tree
Classifier: Development Status :: 5 - Production/Stable
Classifier: Environment :: Web Environment
Classifier: Intended Audience :: Developers
Classifier: License :: OSI Approved :: BSD License
Classifier: Natural Language :: Polish
Classifier: Framework :: Django
Classifier: Framework :: Django :: 3.2
Classifier: Framework :: Django :: 4.1
Classifier: Framework :: Django :: 4.2
Classifier: Programming Language :: Python :: 3
Classifier: Programming Language :: Python :: 3.10
Classifier: Programming Language :: Python :: 3.11
Requires-Python: >=3.10
License-File: LICENSE
License-File: AUTHORS.rst
Requires-Dist: django-mptt
Requires-Dist: django-model-utils
Requires-Dist: django-autoslug
Requires-Dist: tqdm
